ciit_lesson_plan.py
ciit_lesson_plan-0.1.2.dist-info/licenses/LICENSE
ciit_lesson_plan-0.1.2.dist-info/METADATA
ciit_lesson_plan-0.1.2.dist-info/WHEEL
ciit_lesson_plan-0.1.2.dist-info/top_level.txt
ciit_lesson_plan-0.1.2.dist-info/RECORD
