Metadata-Version: 2.4
Name: ciit-lesson-plan
Version: 0.1.2
Summary: 这是一个用于将Markdown格式的教学计划内容转换为Word文档（.docx）的Python脚本。该脚本使用python_docx库来处理Word文档，能够读取Markdown文件内容，并根据预定义的模板生成格式化的教案文档。
Author-email: Yongshun Song <ys_song@foxmail.com>
Maintainer-email: Yongshun Song <ys_song@foxmail.com>
License-Expression: MIT
Keywords: lesson,plan,ciit,teaching,docx
License-File: LICENSE
Requires-Dist: python-docx
Dynamic: license-file
